mr_toolkit/__init__.py
mr_toolkit/_version.py
mr_toolkit/mr_toolkit.py
mr_toolkit/py.typed
mr_toolkit/clustering/__init__.py
mr_toolkit/clustering/stratified_clustering.py
mr_toolkit/coarse_graining/__init__.py
mr_toolkit/coarse_graining/msm_coarse_graining.py
mr_toolkit/reweighting/__init__.py
mr_toolkit/reweighting/analysis.py
mr_toolkit/reweighting/splicing.py
mr_toolkit/tests/__init__.py
mr_toolkit/tests/conftest.py
mr_toolkit/tests/test_analysis.py
mr_toolkit/tests/test_mr_toolkit.py
mr_toolkit/tests/test_msm_coarse_graining.py
mr_toolkit/trajectory_analysis/__init__.py
mr_toolkit/trajectory_analysis/traj_analysis.py
mr_toolkit-0.0.5.dist-info/LICENSE
mr_toolkit-0.0.5.dist-info/METADATA
mr_toolkit-0.0.5.dist-info/WHEEL
mr_toolkit-0.0.5.dist-info/top_level.txt
mr_toolkit-0.0.5.dist-info/RECORD
