Metadata-Version: 2.1
Name: mr-toolkit
Version: 0.0.5
Summary: Tools for reweighted estimation of Markov models.
Author-email: John Russo <mrtoolkit@jdrusso.dev>
License: MIT
Classifier: License :: OSI Approved :: MIT License
Classifier: Programming Language :: Python :: 3
Requires-Python: >=3.8
License-File: LICENSE
Provides-Extra: test
Requires-Dist: pytest (>=6.1.2) ; extra == 'test'
Requires-Dist: pytest-runner ; extra == 'test'
